Metadata-Version: 2.1
Name: bashit
Version: 1.0.0
Summary: put stuff in a file and bash it
Home-page: http://github.com/drorspei/bashit
Author: Dror Speiser
License: MIT
License-File: LICENSE
